octodns_kubernetes/__init__.py
octodns_kubernetes-0.0.1.dist-info/LICENSE
octodns_kubernetes-0.0.1.dist-info/METADATA
octodns_kubernetes-0.0.1.dist-info/WHEEL
octodns_kubernetes-0.0.1.dist-info/top_level.txt
octodns_kubernetes-0.0.1.dist-info/RECORD
