Metadata-Version: 2.1
Name: octodns-kubernetes
Version: 0.0.1
Summary: Kubernetes provider for octoDNS
Home-page: https://github.com/rybnico/octodns-kubernetes
Author: Nicolai Rybnikar
Author-email: octodns-kubernetes@rybnikar.de
License: MIT
Requires-Python: >=3.6
License-File: LICENSE
Requires-Dist: octodns (>=0.9.14)
Requires-Dist: kubernetes (>=25.3.0)
Provides-Extra: dev
Requires-Dist: pytest ; extra == 'dev'
Requires-Dist: pytest-cov ; extra == 'dev'
Requires-Dist: pytest-network ; extra == 'dev'
Requires-Dist: black (>=22.3.0) ; extra == 'dev'
Requires-Dist: build (>=0.7.0) ; extra == 'dev'
Requires-Dist: isort (>=5.11.4) ; extra == 'dev'
Requires-Dist: pyflakes (>=2.2.0) ; extra == 'dev'
Requires-Dist: readme-renderer[md] (>=26.0) ; extra == 'dev'
Requires-Dist: twine (>=3.4.2) ; extra == 'dev'
Provides-Extra: test
Requires-Dist: pytest ; extra == 'test'
Requires-Dist: pytest-cov ; extra == 'test'
Requires-Dist: pytest-network ; extra == 'test'
